simpleinference/__init__.py
simpleinference/infer.py
simpleinference/py.typed
simpleinference-0.0.1.dev5.dist-info/METADATA
simpleinference-0.0.1.dev5.dist-info/WHEEL
simpleinference-0.0.1.dev5.dist-info/RECORD
